examples/__init__.py
examples/gradient_pruning/__init__.py
examples/gradient_pruning/callbacks.py
examples/gradient_pruning/q_models.py
examples/gradient_pruning/trainers.py
test/__init__.py
test/qiskit_plugin_test.py
test/random_layer_test.py
test/static_mode_test.py
test/utils.py
torchquantum/__init__.py
torchquantum/__version__.py
torchquantum/macro.py
torchquantum/algorithm/__init__.py
torchquantum/algorithm/grover.py
torchquantum/algorithm/hamiltonian.py
torchquantum/algorithm/qft.py
torchquantum/algorithm/vqe.py
torchquantum/dataset/__init__.py
torchquantum/dataset/cifar10.py
torchquantum/dataset/layer_regression.py
torchquantum/dataset/mnist.py
torchquantum/dataset/vowel.py
torchquantum/dataset/vqe.py
torchquantum/density/__init__.py
torchquantum/density/density_func.py
torchquantum/density/density_mat.py
torchquantum/density/test.py
torchquantum/device/__init__.py
torchquantum/device/devices.py
torchquantum/device/noisedevices.py
torchquantum/encoding/__init__.py
torchquantum/encoding/encodings.py
torchquantum/functional/__init__.py
torchquantum/functional/ecr.py
torchquantum/functional/func_controlled_unitary.py
torchquantum/functional/func_mat_exp.py
torchquantum/functional/functionals.py
torchquantum/functional/gate_wrapper.py
torchquantum/functional/global_phase.py
torchquantum/functional/hadamard.py
torchquantum/functional/i.py
torchquantum/functional/paulix.py
torchquantum/functional/pauliy.py
torchquantum/functional/pauliz.py
torchquantum/functional/phase_shift.py
torchquantum/functional/qft.py
torchquantum/functional/qubit_unitary.py
torchquantum/functional/r.py
torchquantum/functional/reset.py
torchquantum/functional/rot.py
torchquantum/functional/rx.py
torchquantum/functional/ry.py
torchquantum/functional/rz.py
torchquantum/functional/s.py
torchquantum/functional/single_excitation.py
torchquantum/functional/swap.py
torchquantum/functional/sx.py
torchquantum/functional/t.py
torchquantum/functional/u1.py
torchquantum/functional/u2.py
torchquantum-0.1.8.dist-info/LICENSE
torchquantum-0.1.8.dist-info/METADATA
torchquantum-0.1.8.dist-info/WHEEL
torchquantum-0.1.8.dist-info/top_level.txt
torchquantum-0.1.8.dist-info/RECORD
